{"cameraMode":{"drawMode":0,"name":"Shaded","section":"Shading Mode"},"sceneLighting":true,"audioPlay":false,"sceneViewState":{"showFog":true,"showMaterialUpdate":false,"showSkybox":true,"showFlares":true,"showImageEffects":true,"showParticleSystems":true},"in2DMode":false,"pivot":{"x":-5.824392318725586,"y":1.8095684051513672,"z":86.80431365966797},"rotation":{"x":-0.12159144133329392,"y":0.7644233703613281,"z":-0.15126648545265199,"w":-0.6148744821548462},"size":0.9506369233131409,"orthographic":false}