{"cameraMode":{"drawMode":0,"name":"Shaded","section":"Shading Mode"},"sceneLighting":true,"audioPlay":false,"sceneViewState":{"showFog":true,"showMaterialUpdate":false,"showSkybox":true,"showFlares":true,"showImageEffects":true,"showParticleSystems":true},"in2DMode":false,"pivot":{"x":-9.800566673278809,"y":1.344886064529419,"z":-1.5058990716934205},"rotation":{"x":0.014529982581734658,"y":-0.5739690661430359,"z":-0.010090736672282219,"w":-0.8187716603279114},"size":0.144683837890625,"orthographic":false}